uterm/__init__.py
uterm/actions.py
uterm/browser.py
uterm/comms.py
uterm/main.py
uterm/menu.py
uterm/terminal.py
uterm/tests/__init__.py
uterm/tests/test_actions.py
uterm/tests/test_browser.py
uterm/tests/test_comms.py
uterm/tests/test_menu.py
uterm/tests/test_terminal.py
uterm-0.8.dist-info/DESCRIPTION.rst
uterm-0.8.dist-info/METADATA
uterm-0.8.dist-info/RECORD
uterm-0.8.dist-info/WHEEL
uterm-0.8.dist-info/entry_points.txt
uterm-0.8.dist-info/metadata.json
uterm-0.8.dist-info/top_level.txt
