Metadata-Version: 1.1
Name: uterm
Version: 0.8
Summary: Micropython-friendly terminal
Home-page: https://github.com/SmileyChris/uterm
Author: Chris Beaven
Author-email: smileychris@gmail.com
License: UNKNOWN
Platform: UNKNOWN
Classifier: Development Status :: 3 - Alpha
Classifier: Environment :: Console
Classifier: License :: OSI Approved :: BSD License
Classifier: Operating System :: POSIX
Classifier: Topic :: Software Development :: Embedded Systems
Classifier: Programming Language :: Python
Classifier: Programming Language :: Python :: 2.7
Classifier: Programming Language :: Python :: 3.4
Classifier: Programming Language :: Python :: 3.5
Classifier: Programming Language :: Python :: 3.6
